eml2md/__init__.py
eml2md/__main__.py
eml2md/_main.py
eml2md/_version.py
eml2md/eml.py
eml2md/markdown.py
eml2md/misc.py
eml2md-0.1.2.dist-info/entry_points.txt
eml2md-0.1.2.dist-info/LICENSE
eml2md-0.1.2.dist-info/WHEEL
eml2md-0.1.2.dist-info/METADATA
eml2md-0.1.2.dist-info/RECORD
