Metadata-Version: 2.1
Name: eml2md
Version: 0.1.2
Summary: Convert from eml file to markdown text.
Home-page: https://github.com/elda27/eml2md
License: Apache 2.0
Author: elda27
Author-email: kaz.birdstick@gmail.com
Requires-Python: >=3.8,<3.11
Classifier: License :: Other/Proprietary License
Classifier: Programming Language :: Python :: 3
Classifier: Programming Language :: Python :: 3.8
Classifier: Programming Language :: Python :: 3.9
Classifier: Programming Language :: Python :: 3.10
Project-URL: Repository, https://github.com/elda27/eml2md
